LICENSE
MANIFEST.in
README.md
setup.py
tap_lookml/__init__.py
tap_lookml/client.py
tap_lookml/discover.py
tap_lookml/schema.py
tap_lookml/streams.py
tap_lookml/sync.py
tap_lookml.egg-info/PKG-INFO
tap_lookml.egg-info/SOURCES.txt
tap_lookml.egg-info/dependency_links.txt
tap_lookml.egg-info/entry_points.txt
tap_lookml.egg-info/requires.txt
tap_lookml.egg-info/top_level.txt
tap_lookml/schemas/model_files.json
tap_lookml/schemas/models.json
tap_lookml/schemas/view_files.json
tap_lookml/schemas/views.json