Metadata-Version: 2.1
Name: tap-lookml
Version: 0.0.2
Summary: Singer.io tap for extracting metadata from LookML files with the GitHub API
Home-page: UNKNOWN
Author: jeff.huth@bytecode.io
License: UNKNOWN
Platform: UNKNOWN
Classifier: Programming Language :: Python :: 3 :: Only
Provides-Extra: dev
